pyet_mc-0.3.0.dist-info/METADATA
pyet_mc-0.3.0.dist-info/WHEEL
pyet_mc-0.3.0.dist-info/licenses/LICENSE
pyet_mc/cache/singlecross_10_2pt5_DQ_1000_intrinsic_False_20240827095031.json
pyet_mc/cache/singlecross_10_5pt0_DQ_1000_intrinsic_False_20240827080449.json
pyet_mc/fitting.py
pyet_mc/plotting.py
pyet_mc/plotting_config/ion_colours.csv
pyet_mc/plotting_config/plotting_config.toml
pyet_mc/pyet_utils.py
pyet_mc/structure.py
pyet_mc/__init__.py
pyet_mc/_pyet_mc.cp311-win_amd64.pyd
pyet_mc-0.3.0.dist-info/RECORD
