Metadata-Version: 2.3
Name: pyet_mc
Version: 0.3.0
Classifier: Programming Language :: Rust
Classifier: Programming Language :: Python :: Implementation :: CPython
Classifier: Programming Language :: Python :: Implementation :: PyPy
Requires-Dist: numpy >=1.25.0
Requires-Dist: matplotlib >=3.7.0
Requires-Dist: pandas >=2.0.0
Requires-Dist: plotly >=5.15.0
Requires-Dist: pymatgen >=2024.1.27
Requires-Dist: scipy >=1.11.0
Requires-Dist: toml >=0.10.2
Requires-Dist: pywebview >=4.4.0
Requires-Dist: kaleido >=0.2.0
License-File: LICENSE
Summary: Python package for calculating energy transfer rates between lanthanide ions
Author-email: Jamin Martin <jamin.martin@pg.canterbury.ac.nz>
Maintainer-email: Jamin Martin <jamin.martin@pg.canterbury.ac.nz>
Requires-Python: >=3.11
Project-URL: Homepage, https://github.com/JaminMartin/pyet-mc
Project-URL: Documentation, https://jaminmartin.github.io/pyet-mc/
Project-URL: Repository, https://github.com/JaminMartin/pyet-mc
